pycloc/__init__.py
pycloc/_aliases.py
pycloc/_properties.py
pycloc/_resources.py
pycloc/_serialization.py
pycloc/_subprocess.py
pycloc/_utils.py
pycloc/command.py
pycloc/exceptions.py
pycloc/py.typed
pycloc/resources/__init__.py
pycloc/resources/cloc.ini
pycloc/resources/cloc.pl
pycloc-0.0.1a0.dist-info/METADATA
pycloc-0.0.1a0.dist-info/WHEEL
pycloc-0.0.1a0.dist-info/RECORD
