Metadata-Version: 2.4
Name: pycloc
Version: 0.0.1a0
Summary: Python wrapper for the cloc CLI tool
Project-URL: Documentation, https://pycloc.github.io
Project-URL: Homepage, https://github.com/pycloc
Project-URL: Repository, https://github.com/pycloc/pycloc.git
Project-URL: Issues, https://github.com/pycloc/pycloc/issues
Author-email: Ozren Dabić <dabic.ozren@gmail.com>, Stefano Campanella <stefanocamp187@gmail.com>
License-Expression: MIT
Classifier: Development Status :: 3 - Alpha
Classifier: Intended Audience :: Developers
Classifier: Intended Audience :: Science/Research
Classifier: License :: OSI Approved :: MIT License
Classifier: Operating System :: OS Independent
Classifier: Programming Language :: Python
Classifier: Programming Language :: Python :: 3 :: Only
Classifier: Programming Language :: Python :: 3.10
Classifier: Programming Language :: Python :: 3.11
Classifier: Programming Language :: Python :: 3.12
Classifier: Programming Language :: Python :: 3.13
Requires-Python: >=3.10
